log_scraper-0.9.9-py2.7-nspkg.pth
log_scraper/base.py
log_scraper/consts.py
log_scraper-0.9.9.dist-info/DESCRIPTION.rst
log_scraper-0.9.9.dist-info/metadata.json
log_scraper-0.9.9.dist-info/top_level.txt
log_scraper-0.9.9.dist-info/namespace_packages.txt
log_scraper-0.9.9.dist-info/WHEEL
log_scraper-0.9.9.dist-info/RECORD
log_scraper-0.9.9.dist-info/METADATA
