Metadata-Version: 2.0
Name: log-scraper
Version: 0.9.9
Summary: A base library for writing your own log scraper, i.e. something that can run regexes over files and give you meaningful information like stats. Add your own regexes and plug and play. See the readme for more information.
Home-page: https://github.com/RohitK89/LogScraper/
Author: Rohit Kapur
Author-email: rohitkapur@rohitkapur.com
License: Simplified BSD License
Download-URL: https://github.com/RohitK89/LogScraper/tarball/0.9.6
Keywords: log scraper,logs,regex,stats,grep
Platform: UNIX
Platform: OS X
Platform: Windows
Requires-Dist: paramiko
